ikuzo/__init__.py
ikuzo_python-0.1.5.dist-info/LICENSE
ikuzo_python-0.1.5.dist-info/METADATA
ikuzo_python-0.1.5.dist-info/WHEEL
ikuzo_python-0.1.5.dist-info/top_level.txt
ikuzo_python-0.1.5.dist-info/RECORD
