Metadata-Version: 2.1
Name: ikuzo-python
Version: 0.1.5
Summary: A library to quickly deploy machine learning models to the web
Home-page: https://github.com
Author: Ikuzo
Author-email: tohyongcheng@gmail.com
License: UNKNOWN
Platform: UNKNOWN
Classifier: Programming Language :: Python :: 3
Classifier: License :: OSI Approved :: MIT License
Classifier: Operating System :: OS Independent
Requires-Dist: pubnub (<4,>=3)
Requires-Dist: haikunator
